ai_reliability_analyzer/__init__.py
ai_reliability_analyzer/main.py
ai_reliability_analyzer/prompts.py
ai_reliability_analyzer-2025.12.21171415.dist-info/METADATA
ai_reliability_analyzer-2025.12.21171415.dist-info/WHEEL
ai_reliability_analyzer-2025.12.21171415.dist-info/top_level.txt
ai_reliability_analyzer-2025.12.21171415.dist-info/RECORD
