Metadata-Version: 2.4
Name: ai-reliability-analyzer
Version: 2025.12.21171415
Summary: A new package that analyzes user queries about AI tool reliability and generates structured insights. It takes a text input, such as a question or comment about AI code editor performance issues, and
Author-email: ai-reliability-analyzer <hi@eugene.plus>
License: MIT
Project-URL: Homepage, https://github.com/chigwell/ai-reliability-analyzer
Requires-Python: >=3.9
Requires-Dist: langchain-llm7>=0.0.0
Requires-Dist: llmatch-messages>=0.0.0
Requires-Dist: langchain-core>=0.3.0
